btranslation/__init__.py
btranslation-1.0.1.dist-info/LICENSE.txt
btranslation-1.0.1.dist-info/METADATA
btranslation-1.0.1.dist-info/WHEEL
btranslation-1.0.1.dist-info/top_level.txt
btranslation-1.0.1.dist-info/RECORD
