Metadata-Version: 2.1
Name: btranslation
Version: 1.0.1
Summary: Back Translator using Google translation API
Home-page: UNKNOWN
Author: Sumit Mishra
Author-email: <sumit.mishra0432@gmail.com>
License: MIT
Keywords: python,NLP,back transaltion,text augmentation,google translation API
Platform: UNKNOWN
Classifier: Intended Audience :: Developers
Classifier: Programming Language :: Python :: 3
Classifier: Operating System :: Unix
Classifier: License :: OSI Approved :: MIT License
Classifier: Operating System :: Microsoft :: Windows
Requires-Dist: googletrans
Requires-Dist: numpy
Requires-Dist: pandas
